EffDI/__init__.py
EffDI/__main__.py
EffDI/computation.py
EffDI/compute.py
EffDI/demo_countries.py
EffDI/demo_country.py
EffDI/main.py
EffDI/pre_compute_weights.py
EffDI/visualization.py
effdi-0.1.0.dist-info/LICENSE
effdi-0.1.0.dist-info/METADATA
effdi-0.1.0.dist-info/WHEEL
effdi-0.1.0.dist-info/entry_points.txt
effdi-0.1.0.dist-info/top_level.txt
effdi-0.1.0.dist-info/RECORD
