Metadata-Version: 2.1
Name: effdi
Version: 0.1.0
Summary: Effective dispersion index
Home-page: UNKNOWN
Author: 
Author-email: lukas.herrmann@alumni.ethz.ch
License: UNKNOWN
Platform: UNKNOWN
Classifier: Programming Language :: Python :: 3
Classifier: License :: OSI Approved :: MIT License
Classifier: Operating System :: OS Independent
Requires-Python: >=3.6
License-File: LICENSE
Requires-Dist: numpy
Requires-Dist: matplotlib
Requires-Dist: pandas
Requires-Dist: scipy
Provides-Extra: full
Requires-Dist: sphinx ; extra == 'full'
Requires-Dist: sphinx-rtd-theme ; extra == 'full'
Requires-Dist: pytest ; extra == 'full'
